Metadata-Version: 1.0
Name: jmg-distributions
Version: 0.1
Summary: Gaussian jmg_distributions
Home-page: UNKNOWN
Author: James Gachago
Author-email: myemail@someotherthing.com
License: UNKNOWN
Platform: UNKNOWN
